precinct/__init__.py
precinct/connection.py
precinct/logging.py
precinct/main.py
precinct/models.py
precinct/prompts.yml
precinct-0.1.3.dist-info/LICENSE
precinct-0.1.3.dist-info/METADATA
precinct-0.1.3.dist-info/WHEEL
precinct-0.1.3.dist-info/entry_points.txt
precinct-0.1.3.dist-info/top_level.txt
precinct-0.1.3.dist-info/RECORD
