Metadata-Version: 2.1
Name: precinct
Version: 0.1.3
Summary: Your SQL query AI copilot
Author-email: "mark.snidal@gmail.com" <mark.snidal@gmail.com>
License: GNU GENERAL PUBLIC LICENSE
Project-URL: Homepage, https://github.com/msnidal/precinct
Classifier: Development Status :: 3 - Alpha
Classifier: Environment :: Console
Classifier: Intended Audience :: Developers
Classifier: License :: OSI Approved :: GNU Lesser General Public License v3 or later (LGPLv3+)
Classifier: Operating System :: OS Independent
Classifier: Programming Language :: Python :: 3
Classifier: Programming Language :: Python :: 3.9
Classifier: Programming Language :: Python :: 3 :: Only
Classifier: Programming Language :: SQL
Classifier: Topic :: Database
Classifier: Topic :: Utilities
Requires-Python: >=3.9
License-File: LICENSE
Requires-Dist: psycopg2 ~=2.9
Requires-Dist: types-psycopg2 ~=2.9
Requires-Dist: click ~=8.1
Requires-Dist: openai ~=0.28
Requires-Dist: pydantic ~=2.4
Requires-Dist: sqlparse ~=0.4
Requires-Dist: instructor ~=0.2
Requires-Dist: pyperclip ~=1.8
Requires-Dist: cachetools ~=5.3.2
Requires-Dist: pyyaml ~=6.0
Provides-Extra: dev
Requires-Dist: black ==23.10.0 ; extra == 'dev'
Requires-Dist: isort ==5.12.0 ; extra == 'dev'
